{
  "content_id": "rules_pattern_a_few_weeks_back_someone_t_3c92d4bf",
  "title": "Rules Pattern. A few weeks back, someone tagged me in… | by Ionut Ciuta | The Startup | Medium",
  "url": "https://medium.com/swlh/rules-pattern-1c59854547b",
  "summary": "In his article, Ionut Ciuta discusses the 'Rule Pattern' as a more efficient alternative to using cumbersome if-else statements for managing business rules in programming. He reflects on his experiences with input data validation, particularly in the context of an online shop that needs to apply contextual promotions based on various factors like the contents of a shopping basket and seasonal events. Instead of relying on dense conditional logic, Ciuta advocates for defining rules that encapsulate both the conditions for application and the logic to execute. He provides examples of rules for promotions tied to Halloween and Christmas, demonstrating how this pattern enhances flexibility and maintainability in code. By implementing the Rule Pattern, developers can avoid the pitfalls of hard-to-test and rigid code structures, allowing for easier updates and better organization of decision logic.",
  "key_points": [
    "The Rule Pattern offers a structured approach to managing dynamic business rules, avoiding complex if-else statements.",
    "Defining rules as separate entities allows for better organization and flexibility in applying promotional logic.",
    "The article provides practical examples of how to implement rules for seasonal promotions in an online shop.",
    "Using Spring annotations, the Rule Pattern can be seamlessly integrated into Java applications, enhancing code maintainability.",
    "The approach encourages a more productive programming environment by simplifying decision-making processes."
  ],
  "topics": [
    "Software Development",
    "Design Patterns",
    "Business Logic Management",
    "Java Programming",
    "Code Maintainability"
  ],
  "word_count": 134,
  "original_word_count": 2431,
  "compression_ratio": 0.055121349238996295,
  "confidence_score": 0.9
}